warmth/__init__.py
warmth/build.py
warmth/data/haq87.json
warmth/data.py
warmth/forward_modelling.py
warmth/logging.py
warmth/mesh_model.py
warmth/mesh_utils.py
warmth/model.py
warmth/parameters.py
warmth/postprocessing.py
warmth/resqpy_helpers.py
warmth/simulator.py
warmth/utils.py
warmth-0.0.24.dist-info/METADATA
warmth-0.0.24.dist-info/WHEEL
warmth-0.0.24.dist-info/licenses/LICENSE.md
warmth-0.0.24.dist-info/RECORD
