Metadata-Version: 2.4
Name: warmth
Version: 0.0.24
Summary: 
License-File: LICENSE.md
Author: Adam Cheng
Author-email: 52572642+adamchengtkc@users.noreply.github.com
Requires-Python: >=3.10,<3.13
Classifier: Programming Language :: Python :: 3
Classifier: Programming Language :: Python :: 3.10
Classifier: Programming Language :: Python :: 3.11
Classifier: Programming Language :: Python :: 3.12
Requires-Dist: meshio[all] (>=5.3.4,<6.0.0)
Requires-Dist: numpy (>=1.26.0,<2.0.0)
Requires-Dist: pandas (>=2.3.0,<3.0.0)
Requires-Dist: pillow (>=10.3.0,<11.0.0)
Requires-Dist: progress (>=1.6,<2.0)
Requires-Dist: resqpy (>=5.1.10,<6.0.0)
Requires-Dist: scipy (>=1.11.3,<2.0.0)
Requires-Dist: urllib3 (>=2.0.6,<3.0.0)
Requires-Dist: xtgeo (>=4.0.0)
